quadtree_rs-0.4.0.dist-info/METADATA
quadtree_rs-0.4.0.dist-info/WHEEL
quadtree_rs-0.4.0.dist-info/licenses/LICENSE
quadtree_rs/__init__.py
quadtree_rs/__init__.pyi
quadtree_rs/_bimap.py
quadtree_rs/_item.py
quadtree_rs/_native.abi3.so
quadtree_rs/py.typed
quadtree_rs-0.4.0.dist-info/RECORD
