Metadata-Version: 2.4
Name: quadtree_rs
Version: 0.4.0
Classifier: Programming Language :: Python :: 3
Classifier: Programming Language :: Python :: 3 :: Only
Classifier: Programming Language :: Rust
Classifier: Programming Language :: Python :: Implementation :: CPython
Classifier: Operating System :: OS Independent
Classifier: Topic :: Scientific/Engineering
Classifier: Topic :: Scientific/Engineering :: Information Analysis
Classifier: Topic :: Software Development :: Libraries
Classifier: Typing :: Typed
Classifier: License :: OSI Approved :: MIT License
License-File: LICENSE
Summary: Rust-accelerated quadtree for Python with fast inserts, range queries, and k-NN search.
Keywords: quadtree,spatial-index,geometry,rust,pyo3,nearest-neighbor,k-nn
Author: Ethan Anderson
Requires-Python: >=3.8
Project-URL: Homepage, https://github.com/Elan456/quadtree-rs
Project-URL: Repository, https://github.com/Elan456/quadtree-rs
Project-URL: Issues, https://github.com/Elan456/quadtree-rs/issues
